Astryl/__init__.py
Astryl/node_queries.py
Astryl/operations.py
Astryl/sql.py
Astryl/utils.py
Astryl-0.1.1.dist-info/LICENSE
Astryl-0.1.1.dist-info/METADATA
Astryl-0.1.1.dist-info/WHEEL
Astryl-0.1.1.dist-info/top_level.txt
Astryl-0.1.1.dist-info/RECORD
