Metadata-Version: 2.1
Name: Astryl
Version: 0.1.1
Summary: A library for managing Neo4j operations.
Home-page: https://github.com/Krater-Group/Astryl
Author: Heinrich Schanckenberg
Author-email: heinrich2cs@gmail.com
Classifier: Programming Language :: Python :: 3
Classifier: License :: OSI Approved :: MIT License
Classifier: Operating System :: OS Independent
Requires-Python: >=3.6
License-File: LICENSE
Requires-Dist: neo4j
Requires-Dist: pandas
